artpack/__init__.py
artpack/_utils.py
artpack/circles.py
artpack/palettes.py
artpack-0.2.0.post1.dist-info/METADATA
artpack-0.2.0.post1.dist-info/WHEEL
artpack-0.2.0.post1.dist-info/licenses/LICENSE
artpack-0.2.0.post1.dist-info/RECORD
