Metadata-Version: 2.4
Name: artpack
Version: 0.2.0.post1
Summary: Create data that displays generative art when mapped into a 'plotnine' plot. Functionality includes specialized data frame creation for geometric shapes, tools that define artistic color palettes, tools for geometrically transforming data, and other miscellaneous tools that are helpful when using 'plotnine' for generative art.
Project-URL: Homepage, https://github.com/Meghansaha/artpack-py
Project-URL: Repository, https://github.com/Meghansaha/artpack-py
Author-email: "Meghan S. Harris" <meghanha01@gmail.com>
License-File: LICENSE
Requires-Python: >=3.10
Requires-Dist: build>=1.3.0
Requires-Dist: matplotlib==3.8.4
Requires-Dist: numpy==1.26.4
Requires-Dist: pandas==2.2.2
Requires-Dist: plotnine>=0.12.0
Requires-Dist: polars
Requires-Dist: pyarrow
Provides-Extra: dev
Requires-Dist: pytest-cov>=4.0; extra == 'dev'
Requires-Dist: pytest>=7.0; extra == 'dev'
Requires-Dist: quartodoc; extra == 'dev'
Requires-Dist: twine; extra == 'dev'
